dom_locator/__init__.py
dom_locator/dom_source.py
dom_locator/exceptions.py
dom_locator/locator.py
dom_locator-0.0.2.dist-info/licenses/LICENSE
dom_locator-0.0.2.dist-info/METADATA
dom_locator-0.0.2.dist-info/WHEEL
dom_locator-0.0.2.dist-info/top_level.txt
dom_locator-0.0.2.dist-info/RECORD
