Metadata-Version: 2.4
Name: dom-locator
Version: 0.0.2
Summary: Library for interacting with XML and HTML DOM 
Home-page: https://github.com/VBenevides/dom-locator
Author: Vinicius Benevides
Author-email: viniciusm.benevides@gmail.com
License: MIT
License-File: LICENSE
Requires-Dist: lxml
Dynamic: author
Dynamic: author-email
Dynamic: home-page
Dynamic: license
Dynamic: license-file
Dynamic: requires-dist
Dynamic: summary
